superpilot/__init__.py
superpilot/main.py
superpilot/app/__init__.py
superpilot/app/cli_app/__init__.py
superpilot/app/cli_app/cli.py
superpilot/app/cli_app/main.py
superpilot/app/cli_web_app/__init__.py
superpilot/app/cli_web_app/cli.py
superpilot/app/cli_web_app/client/__init__.py
superpilot/app/cli_web_app/client/client.py
superpilot/app/cli_web_app/server/__init__.py
superpilot/app/cli_web_app/server/api.py
superpilot/app/cli_web_app/server/schema.py
superpilot/app/cli_web_app/server/services/__init__.py
superpilot/app/cli_web_app/server/services/users.py
superpilot/app/client_lib/__init__.py
superpilot/app/client_lib/logging.py
superpilot/app/client_lib/settings.py
superpilot/app/client_lib/shared_click_commands.py
superpilot/app/client_lib/utils.py
superpilot/core/__init__.py
superpilot/core/singleton.py
superpilot/core/status.py
superpilot/core/_deprecated/__init__.py
superpilot/core/_deprecated/messaging/__init__.py
superpilot/core/_deprecated/messaging/base.py
superpilot/core/_deprecated/messaging/simple.py
superpilot/core/ability/__init__.py
superpilot/core/ability/base.py
superpilot/core/ability/schema.py
superpilot/core/ability/simple.py
superpilot/core/ability/super.py
superpilot/core/ability/builtins/__init__.py
superpilot/core/ability/builtins/create_new_ability.py
superpilot/core/ability/builtins/file_operations.py
superpilot/core/ability/builtins/image_operations.py
superpilot/core/ability/builtins/query_language_model.py
superpilot/core/ability/builtins/super.py
superpilot/core/agent/__init__.py
superpilot/core/agent/base.py
superpilot/core/agent/research.py
superpilot/core/agent/settings.py
superpilot/core/agent/simple.py
superpilot/core/app/__init__.py
superpilot/core/app/app_manager.py
superpilot/core/app/executor.py
superpilot/core/app/plugin_loader.py
superpilot/core/app/thread_manager.py
superpilot/core/block/__init__.py
superpilot/core/block/base.py
superpilot/core/block/simple.py
superpilot/core/block/execution/__init__.py
superpilot-0.5.2.dist-info/LICENSE
superpilot-0.5.2.dist-info/METADATA
superpilot-0.5.2.dist-info/WHEEL
superpilot-0.5.2.dist-info/top_level.txt
superpilot-0.5.2.dist-info/RECORD
