Metadata-Version: 2.1
Name: superpilot
Version: 0.5.2
Summary: The Multi-Role Superpilot Programming Framework
Home-page: https://github.com/parvbhullar/superpilot
Author: ParvBhullar
Author-email: parvinder@recalll.co
License: MIT
Keywords: superpilot multi-role multi-agent programming gpt llm
Requires-Python: >=3.10
License-File: LICENSE
Requires-Dist: abstract-singleton
Requires-Dist: aiohappyeyeballs
Requires-Dist: aiohttp
Requires-Dist: aiosignal
Requires-Dist: alembic
Requires-Dist: annotated-types
Requires-Dist: anthropic
Requires-Dist: antlr4-python3-runtime
Requires-Dist: anyio
Requires-Dist: appdirs
Requires-Dist: argon2-cffi
Requires-Dist: argon2-cffi-bindings
Requires-Dist: async-timeout
Requires-Dist: attrs
Requires-Dist: auto-gpt-plugin-template
Requires-Dist: autoflake
Requires-Dist: azure-core
Requires-Dist: azure-identity
Requires-Dist: backoff
Requires-Dist: backports.tarfile
Requires-Dist: bcrypt
Requires-Dist: beanie
Requires-Dist: beautifulsoup4
Requires-Dist: bert-extractive-summarizer
Requires-Dist: black
Requires-Dist: Brotli
Requires-Dist: cachetools
Requires-Dist: catalogue
Requires-Dist: certifi
Requires-Dist: cffi
Requires-Dist: cfgv
Requires-Dist: chardet
Requires-Dist: charset-normalizer
Requires-Dist: click
Requires-Dist: click-log
Requires-Dist: cloudpathlib
Requires-Dist: colorama
Requires-Dist: coloredlogs
Requires-Dist: colorlog
Requires-Dist: confection
Requires-Dist: contourpy
Requires-Dist: cryptography
Requires-Dist: cssselect
Requires-Dist: cssselect2
Requires-Dist: cycler
Requires-Dist: cymem
Requires-Dist: Cython
Requires-Dist: dataclasses-json
Requires-Dist: datasets
Requires-Dist: decorator
Requires-Dist: Deprecated
Requires-Dist: deprecation
Requires-Dist: dill
Requires-Dist: dirtyjson
Requires-Dist: diskcache
Requires-Dist: distlib
Requires-Dist: distro
Requires-Dist: dnspython
Requires-Dist: docker
Requires-Dist: docopt
Requires-Dist: docutils
Requires-Dist: docx
Requires-Dist: docx2txt
Requires-Dist: dotty-dict
Requires-Dist: dspy
Requires-Dist: ecdsa
Requires-Dist: effdet
Requires-Dist: email-validator
Requires-Dist: emoji
Requires-Dist: et-xmlfile
Requires-Dist: eval-type-backport
Requires-Dist: exceptiongroup
Requires-Dist: faiss-cpu
Requires-Dist: fastapi
Requires-Dist: fastapi-users
Requires-Dist: fastapi-users-db-beanie
Requires-Dist: fastapi-users-db-sqlalchemy
Requires-Dist: feedfinder2
Requires-Dist: feedparser
Requires-Dist: filelock
Requires-Dist: filetype
Requires-Dist: FLAML
Requires-Dist: flatbuffers
Requires-Dist: fonttools
Requires-Dist: frozenlist
Requires-Dist: fsspec
Requires-Dist: future
Requires-Dist: gitdb
Requires-Dist: GitPython
Requires-Dist: google-api-core
Requires-Dist: google-api-python-client
Requires-Dist: google-auth
Requires-Dist: google-auth-httplib2
Requires-Dist: google-cloud-vision
Requires-Dist: google-search-results
Requires-Dist: googleapis-common-protos
Requires-Dist: gotrue
Requires-Dist: greenlet
Requires-Dist: grpcio
Requires-Dist: grpcio-status
Requires-Dist: gTTS
Requires-Dist: h11
Requires-Dist: h2
Requires-Dist: hpack
Requires-Dist: html5lib
Requires-Dist: httpcore
Requires-Dist: httplib2
Requires-Dist: httpx
Requires-Dist: humanfriendly
Requires-Dist: hyperframe
Requires-Dist: identify
Requires-Dist: idna
Requires-Dist: importlib-resources
Requires-Dist: importlib-metadata
Requires-Dist: inflection
Requires-Dist: invoke
Requires-Dist: iopath
Requires-Dist: isort
Requires-Dist: jaraco.classes
Requires-Dist: jaraco.context
Requires-Dist: jaraco.functools
Requires-Dist: jeepney
Requires-Dist: jieba3k
Requires-Dist: Jinja2
Requires-Dist: jiter
Requires-Dist: joblib
Requires-Dist: jsonpatch
Requires-Dist: jsonpath-python
Requires-Dist: jsonpointer
Requires-Dist: jsonschema
Requires-Dist: jsonschema-specifications
Requires-Dist: keyring
Requires-Dist: kiwisolver
Requires-Dist: in
Requires-Dist: language-data
Requires-Dist: layoutparser
Requires-Dist: lazy-model
Requires-Dist: libmagic
Requires-Dist: litellm
Requires-Dist: llama-cloud
Requires-Dist: llama-index
Requires-Dist: llama-index-agent-openai
Requires-Dist: llama-index-cli
Requires-Dist: llama-index-core
Requires-Dist: llama-index-embeddings-openai
Requires-Dist: llama-index-graph-stores-nebula
Requires-Dist: llama-index-indices-managed-llama-cloud
Requires-Dist: llama-index-legacy
Requires-Dist: llama-index-llms-azure-openai
Requires-Dist: llama-index-llms-openai
Requires-Dist: llama-index-multi-modal-llms-openai
Requires-Dist: llama-index-program-openai
Requires-Dist: llama-index-question-gen-openai
Requires-Dist: llama-index-readers-file
Requires-Dist: llama-index-readers-llama-parse
Requires-Dist: llama-parse
Requires-Dist: lxml
Requires-Dist: magicattr
Requires-Dist: makefun
Requires-Dist: Mako
Requires-Dist: marisa-trie
Requires-Dist: markdown-it-py
Requires-Dist: markdown2
Requires-Dist: MarkupSafe
Requires-Dist: marshmallow
Requires-Dist: matplotlib
Requires-Dist: md2pdf
Requires-Dist: mdurl
Requires-Dist: more-itertools
Requires-Dist: motor
Requires-Dist: mpmath
Requires-Dist: msal
Requires-Dist: msal-extensions
Requires-Dist: multidict
Requires-Dist: multiprocess
Requires-Dist: murmurhash
Requires-Dist: mypy-extensions
Requires-Dist: ndg-httpsclient
Requires-Dist: nebula3-python
Requires-Dist: nest-asyncio
Requires-Dist: networkx
Requires-Dist: newspaper3k
Requires-Dist: nh3
Requires-Dist: nltk
Requires-Dist: nodeenv
Requires-Dist: numexpr
Requires-Dist: numpy
Requires-Dist: oauthlib
Requires-Dist: odmantic
Requires-Dist: olefile
Requires-Dist: omegaconf
Requires-Dist: onnx
Requires-Dist: openai
Requires-Dist: openapi-python-client
Requires-Dist: openapi-schema-pydantic
Requires-Dist: opencv-python
Requires-Dist: openpyxl
Requires-Dist: optuna
Requires-Dist: orjson
Requires-Dist: outcome
Requires-Dist: packaging
Requires-Dist: pandas
Requires-Dist: passlib
Requires-Dist: pathspec
Requires-Dist: pdf2image
Requires-Dist: pdfminer.six
Requires-Dist: pdfplumber
Requires-Dist: pi-heif
Requires-Dist: pikepdf
Requires-Dist: pillow
Requires-Dist: pkginfo
Requires-Dist: platformdirs
Requires-Dist: playwright
Requires-Dist: portalocker
Requires-Dist: postgrest
Requires-Dist: pre-commit
Requires-Dist: preshed
Requires-Dist: prompt-toolkit
Requires-Dist: proto-plus
Requires-Dist: protobuf
Requires-Dist: psutil
Requires-Dist: pwdlib
Requires-Dist: py
Requires-Dist: pyarrow
Requires-Dist: pyasn1
Requires-Dist: pyasn1-modules
Requires-Dist: pycocotools
Requires-Dist: pycparser
Requires-Dist: pydantic
Requires-Dist: pydantic-settings
Requires-Dist: pydantic-core
Requires-Dist: pydyf
Requires-Dist: pyee
Requires-Dist: pyflakes
Requires-Dist: Pygments
Requires-Dist: PyJWT
Requires-Dist: pymongo
Requires-Dist: PyMuPDF
Requires-Dist: PyMuPDFb
Requires-Dist: pyOpenSSL
Requires-Dist: pyparsing
Requires-Dist: pypdf
Requires-Dist: PyPDF2
Requires-Dist: pypdfium2
Requires-Dist: pyphen
Requires-Dist: pysbd
Requires-Dist: PySocks
Requires-Dist: pytesseract
Requires-Dist: python-dateutil
Requires-Dist: python-docx
Requires-Dist: python-dotenv
Requires-Dist: python-gitlab
Requires-Dist: python-iso639
Requires-Dist: python-jose
Requires-Dist: python-magic
Requires-Dist: python-multipart
Requires-Dist: python-oxmsg
Requires-Dist: python-pptx
Requires-Dist: python-semantic-release
Requires-Dist: pytz
Requires-Dist: pyvespa
Requires-Dist: PyYAML
Requires-Dist: ragas
Requires-Dist: RapidFuzz
Requires-Dist: readme-renderer
Requires-Dist: realtime
Requires-Dist: referencing
Requires-Dist: regex
Requires-Dist: requests
Requires-Dist: requests-file
Requires-Dist: requests-oauthlib
Requires-Dist: requests-toolbelt
Requires-Dist: retry
Requires-Dist: retrying
Requires-Dist: rfc3986
Requires-Dist: rich
Requires-Dist: rpds-py
Requires-Dist: rsa
Requires-Dist: safetensors
Requires-Dist: scikit-learn
Requires-Dist: scipy
Requires-Dist: SecretStorage
Requires-Dist: selenium
Requires-Dist: semver
Requires-Dist: sentence-transformers
Requires-Dist: sgmllib3k
Requires-Dist: shellingham
Requires-Dist: six
Requires-Dist: smart-open
Requires-Dist: smmap
Requires-Dist: sniffio
Requires-Dist: sortedcontainers
Requires-Dist: soupsieve
Requires-Dist: spacy
Requires-Dist: spacy-legacy
Requires-Dist: spacy-loggers
Requires-Dist: SQLAlchemy
Requires-Dist: srsly
Requires-Dist: starlette
Requires-Dist: storage3
Requires-Dist: StrEnum
Requires-Dist: striprtf
Requires-Dist: structlog
Requires-Dist: supabase
Requires-Dist: supafunc
Requires-Dist: sympy
Requires-Dist: tabulate
Requires-Dist: tenacity
Requires-Dist: termcolor
Requires-Dist: thinc
Requires-Dist: threadpoolctl
Requires-Dist: tiktoken
Requires-Dist: timm
Requires-Dist: tinycss2
Requires-Dist: tinysegmenter
Requires-Dist: tldextract
Requires-Dist: tokenizers
Requires-Dist: toml
Requires-Dist: tomli
Requires-Dist: tomlkit
Requires-Dist: torch
Requires-Dist: torchaudio
Requires-Dist: torchvision
Requires-Dist: tqdm
Requires-Dist: transformers
Requires-Dist: trio
Requires-Dist: trio-websocket
Requires-Dist: tweepy
Requires-Dist: twine
Requires-Dist: typer
Requires-Dist: typing-inspect
Requires-Dist: typing-extensions
Requires-Dist: tzdata
Requires-Dist: ujson
Requires-Dist: unstructured
Requires-Dist: unstructured-client
Requires-Dist: unstructured-inference
Requires-Dist: unstructured.pytesseract
Requires-Dist: uritemplate
Requires-Dist: urllib3
Requires-Dist: urllib3-secure-extra
Requires-Dist: uvicorn
Requires-Dist: vespacli
Requires-Dist: virtualenv
Requires-Dist: wasabi
Requires-Dist: wcwidth
Requires-Dist: weasel
Requires-Dist: weasyprint
Requires-Dist: webdriver-manager
Requires-Dist: webencodings
Requires-Dist: websocket-client
Requires-Dist: websockets
Requires-Dist: wrapt
Requires-Dist: wsproto
Requires-Dist: XlsxWriter
Requires-Dist: xxhash
Requires-Dist: yarl
Requires-Dist: zipp
Requires-Dist: zopfli
Requires-Dist: langsmith==0.1.102
Requires-Dist: transformers<5.0.0,>=4.41.0
Requires-Dist: setfit>=0.1.0
